MANIFEST.in
README.md
setup.py
ExcelLib.egg-info/PKG-INFO
ExcelLib.egg-info/SOURCES.txt
ExcelLib.egg-info/dependency_links.txt
ExcelLib.egg-info/requires.txt
ExcelLib.egg-info/top_level.txt
src/ExcelLib/__init__.py
src/ExcelLib/excellib.txt